peeringdb/__init__.py
peeringdb/_sync.py
peeringdb/_update.py
peeringdb/backend.py
peeringdb/cli.py
peeringdb/client.py
peeringdb/commands.py
peeringdb/config.py
peeringdb/fetch.py
peeringdb/private.py
peeringdb/py.typed
peeringdb/resource.py
peeringdb/util.py
peeringdb/whois.py
peeringdb/_debug/__init__.py
peeringdb/_debug/http.py
peeringdb/output/__init__.py
peeringdb/output/_dict.py
peeringdb-2.4.1.dist-info/METADATA
peeringdb-2.4.1.dist-info/WHEEL
peeringdb-2.4.1.dist-info/entry_points.txt
peeringdb-2.4.1.dist-info/licenses/LICENSE.txt
peeringdb-2.4.1.dist-info/RECORD
