Metadata-Version: 2.4
Name: peeringdb
Version: 2.4.1
Summary: PeeringDB Python client and library
Project-URL: repository, https://github.com/peeringdb/peeringdb-py
Project-URL: homepage, https://www.peeringdb.com
Project-URL: documentation, https://peeringdb.github.io/peeringdb-py
Project-URL: changelog, https://github.com/peeringdb/peeringdb-py/blob/master/CHANGELOG.md
Project-URL: issues, https://github.com/peeringdb/peeringdb-py/issues
Author-email: PeeringDB <support@peeringdb.com>
License: BSD-2-Clause
License-File: LICENSE.txt
Keywords: api,asn,bgp,internet,networking,peering,peeringdb
Classifier: Development Status :: 5 - Production/Stable
Classifier: Intended Audience :: Developers
Classifier: Intended Audience :: System Administrators
Classifier: Intended Audience :: Telecommunications Industry
Classifier: License :: OSI Approved :: BSD License
Classifier: Programming Language :: Python :: 3.9
Classifier: Programming Language :: Python :: 3.10
Classifier: Programming Language :: Python :: 3.11
Classifier: Programming Language :: Python :: 3.12
Classifier: Programming Language :: Python :: 3.13
Classifier: Topic :: Internet
Classifier: Topic :: Software Development :: Libraries :: Python Modules
Requires-Python: >=3.9
Requires-Dist: confu>=1
Requires-Dist: httpx>=0.24.1
Requires-Dist: munge[toml,tomlkit,yaml]>=1.2.0
Requires-Dist: pyyaml>=6.0.1
Requires-Dist: twentyc-rpc>=1
